amtutorial/__init__.py
amtutorial/_modidx.py
amtutorial/data_utils.py
amtutorial/path_fixes.py
amtutorial-0.0.8.dist-info/METADATA
amtutorial-0.0.8.dist-info/WHEEL
amtutorial-0.0.8.dist-info/entry_points.txt
amtutorial-0.0.8.dist-info/licenses/LICENSE
amtutorial-0.0.8.dist-info/RECORD
