Metadata-Version: 2.4
Name: amtutorial
Version: 0.0.8
Summary: Add your description here
Author-email: Ben Hoover <24350185+bhoov@users.noreply.github.com>
License-File: LICENSE
Requires-Python: >=3.9
Requires-Dist: beautifulsoup4>=4.13.4
Requires-Dist: einops>=0.8.1
Requires-Dist: equinox>=0.11.10
Requires-Dist: ffmpeg-python>=0.2.0
Requires-Dist: gdown>=5.2.0
Requires-Dist: imageio>=2.37.0
Requires-Dist: ipywidgets>=8.1.7
Requires-Dist: jax>=0.4.30
Requires-Dist: matplotlib>=3.9.4
Requires-Dist: moviepy<2.0
Requires-Dist: opencv-python>=4.11.0.86
Requires-Dist: scikit-learn>=1.6.1
Requires-Dist: scipy>=1.13.1
Requires-Dist: seaborn>=0.13.2
Requires-Dist: tqdm>=4.67.1
